tests/__init__.py
tests/test_core.py
tests/test_functions.py
tests/test_untyped.py
tests/typecube/__init__.py
tests/typecube/annotations.py
tests/typecube/core.py
tests/typecube/errors.py
tests/typecube/ext.py
tests/typecube/resolvers.py
tests/typecube/typed.py
tests/typecube/unifier.py
tests/typecube/untyped.py
tests/typecube/utils.py
typecube/__init__.py
typecube/annotations.py
typecube/core.py
typecube/errors.py
typecube/ext.py
typecube/resolvers.py
typecube/typed.py
typecube/unifier.py
typecube/untyped.py
typecube/utils.py
typecube-0.0.1.data/scripts/clean_install.sh
typecube-0.0.1.data/scripts/package.sh
typecube-0.0.1.dist-info/DESCRIPTION.rst
typecube-0.0.1.dist-info/METADATA
typecube-0.0.1.dist-info/RECORD
typecube-0.0.1.dist-info/WHEEL
typecube-0.0.1.dist-info/metadata.json
typecube-0.0.1.dist-info/top_level.txt
