Metadata-Version: 2.0
Name: typecube
Version: 0.0.1
Summary: Utilities and library to model types and type systems
Home-page: https://github.com/panyam/typecube
Author: Sriram Panyam
Author-email: sri.panyam@gmail.com
License: BSD
Keywords: languages,type system,types
Platform: UNKNOWN
Classifier: Development Status :: 2 - Pre-Alpha
Classifier: Intended Audience :: Developers
Classifier: License :: OSI Approved :: BSD License
Classifier: Operating System :: OS Independent
Classifier: Programming Language :: Python
Classifier: Programming Language :: Python :: 2
Classifier: Programming Language :: Python :: 2.7
Classifier: Topic :: Internet :: WWW/HTTP
Classifier: Topic :: Internet :: WWW/HTTP :: Dynamic Content
Classifier: Topic :: Internet :: WWW/HTTP :: WSGI
Classifier: Topic :: Software Development :: Libraries :: Application Frameworks
Classifier: Topic :: Software Development :: Libraries :: Python Modules
Classifier: Topic :: Software Development :: Code Generators
Classifier: Topic :: Software Development :: Compilers
Requires: enum34
Requires: ipdb
Requires: wheel
Requires: PyYaml
Provides-Extra: docs
Requires-Dist: Sphinx (>=1.1); extra == 'docs'
